odoo/addons/pos_environment/README.rst
odoo/addons/pos_environment/__init__.py
odoo/addons/pos_environment/__manifest__.py
odoo/addons/pos_environment/i18n/de.po
odoo/addons/pos_environment/i18n/fr.po
odoo/addons/pos_environment/i18n/it.po
odoo/addons/pos_environment/i18n/pos_environment.pot
odoo/addons/pos_environment/models/__init__.py
odoo/addons/pos_environment/models/pos_config.py
odoo/addons/pos_environment/models/res_config_settings.py
odoo/addons/pos_environment/readme/CONFIGURE.rst
odoo/addons/pos_environment/readme/CONTRIBUTORS.rst
odoo/addons/pos_environment/readme/DESCRIPTION.rst
odoo/addons/pos_environment/static/description/icon.png
odoo/addons/pos_environment/static/description/index.html
odoo/addons/pos_environment/static/description/receipt.png
odoo/addons/pos_environment/static/description/res_config_settings_form.png
odoo/addons/pos_environment/static/src/xml/ReceiptScreen.xml
odoo/addons/pos_environment/views/res_config_settings_views.xml
odoo_addon_pos_environment-16.0.1.0.1.6.dist-info/METADATA
odoo_addon_pos_environment-16.0.1.0.1.6.dist-info/WHEEL
odoo_addon_pos_environment-16.0.1.0.1.6.dist-info/top_level.txt
odoo_addon_pos_environment-16.0.1.0.1.6.dist-info/RECORD
