Metadata-Version: 2.1
Name: odoo-addon-pos_environment
Version: 16.0.1.0.1.6
Summary: Custom messages on the bill depending on the environment
Home-page: https://github.com/OCA/server-env
Author: GRAP,Odoo Community Association (OCA)
Author-email: support@odoo-community.org
License: AGPL-3
Classifier: Programming Language :: Python
Classifier: Framework :: Odoo
Classifier: Framework :: Odoo :: 16.0
Classifier: License :: OSI Approved :: GNU Affero General Public License v3
Requires-Python: >=3.10
Requires-Dist: odoo-addon-server-environment<16.1dev,>=16.0dev
Requires-Dist: odoo<16.1dev,>=16.0a
